[
    {
        "label": "PSC",
        "value": "PSC"
    },
    {
        "label": "UNIÃO",
        "value": "UNIÃO"
    },
    {
        "label": "MDB",
        "value": "MDB"
    },
    {
        "label": "PSDB",
        "value": "PSDB"
    },
    {
        "label": "NOVO",
        "value": "NOVO"
    },
    {
        "label": "PP",
        "value": "PP"
    },
    {
        "label": "PT",
        "value": "PT"
    },
    {
        "label": "PDT",
        "value": "PDT"
    },
    {
        "label": "PATRIOTA",
        "value": "PATRIOTA"
    },
    {
        "label": "REPUBLICANOS",
        "value": "REPUBLICANOS"
    },
    {
        "label": "PSB",
        "value": "PSB"
    },
    {
        "label": "CIDADANIA",
        "value": "CIDADANIA"
    },
    {
        "label": "PSD",
        "value": "PSD"
    },
    {
        "label": "PROS",
        "value": "PROS"
    },
    {
        "label": "PCdoB",
        "value": "PCdoB"
    },
    {
        "label": "PV",
        "value": "PV"
    },
    {
        "label": "PL",
        "value": "PL"
    },
    {
        "label": "AVANTE",
        "value": "AVANTE"
    },
    {
        "label": "PSOL",
        "value": "PSOL"
    },
    {
        "label": "SOLIDARIEDADE",
        "value": "SOLIDARIEDADE"
    },
    {
        "label": "PTB",
        "value": "PTB"
    },
    {
        "label": "PODE",
        "value": "PODE"
    },
    {
        "label": "REDE",
        "value": "REDE"
    }
]